test-deploy-package/__init__.py
test-deploy-package/test_deploy.py
test_deploy_package/__init__.py
test_deploy_package/test_deploy.py
test_deploy_package-1.0.8.dist-info/LICENSE
test_deploy_package-1.0.8.dist-info/METADATA
test_deploy_package-1.0.8.dist-info/WHEEL
test_deploy_package-1.0.8.dist-info/entry_points.txt
test_deploy_package-1.0.8.dist-info/top_level.txt
test_deploy_package-1.0.8.dist-info/RECORD
