Metadata-Version: 2.1
Name: test-deploy-package
Version: 1.0.8
Summary: Demo
Home-page: https://github.com/Qili-test/test-deploy
Author: Qi
Author-email: lihqih@gmail.com
License: MIT
Keywords: test deploy
Platform: UNKNOWN
Classifier: Programming Language :: Python :: 3
Classifier: License :: OSI Approved :: MIT License
Classifier: Operating System :: OS Independent
Requires-Dist: dill (==0.2.9)
Requires-Dist: numpy (==1.16.2)
Requires-Dist: DateTime (==4.3)
Requires-Dist: pandas (==0.24.2)
Requires-Dist: scikit-learn (==0.20.3)
Requires-Dist: scipy (==1.2.1)
Requires-Dist: xgboost (==0.90)
